pyneg/__init__.py
pyneg/agent/__init__.py
pyneg/agent/agent.py
pyneg/agent/agent_factory.py
pyneg/agent/constr_agent.py
pyneg/comms/__init__.py
pyneg/comms/atomic_constraint.py
pyneg/comms/message.py
pyneg/comms/offer.py
pyneg/engine/__init__.py
pyneg/engine/constrained_dtp_generator.py
pyneg/engine/constrained_enum_generator.py
pyneg/engine/constrained_linear_evaluator.py
pyneg/engine/constrained_problog_evaluator.py
pyneg/engine/constrained_random_generator.py
pyneg/engine/dtp_generator.py
pyneg/engine/engine.py
pyneg/engine/enum_generator.py
pyneg/engine/evaluator.py
pyneg/engine/generator.py
pyneg/engine/linear_evaluator.py
pyneg/engine/problog_evaluator.py
pyneg/engine/random_generator.py
pyneg/engine/strategy.py
pyneg/types/__init__.py
pyneg/types/message_type.py
pyneg/types/verbosity.py
pyneg/utils/__init__.py
pyneg/utils/utils.py
pyneg-1.0.2.dist-info/METADATA
pyneg-1.0.2.dist-info/WHEEL
pyneg-1.0.2.dist-info/top_level.txt
pyneg-1.0.2.dist-info/RECORD
