Metadata-Version: 2.1
Name: pyneg
Version: 1.0.2
Summary: A python package for simulating automated negotiations
Home-page: https://github.com/dvente/pyneg
Author: Sam Vente
Author-email: savente93@gmail.com
License: UNKNOWN
Platform: UNKNOWN
Classifier: Programming Language :: Python :: 3
Classifier: License :: OSI Approved :: MIT License
Classifier: Operating System :: OS Independent
Requires-Python: >=3.6
Requires-Dist: numpy
Requires-Dist: problog
